lymph/__init__.py
lymph/_version.py
lymph/diagnosis_times.py
lymph/graph.py
lymph/matrix.py
lymph/modalities.py
lymph/types.py
lymph/utils.py
lymph/models/__init__.py
lymph/models/bilateral.py
lymph/models/hpv.py
lymph/models/midline.py
lymph/models/unilateral.py
lymph_model-1.3.7.dist-info/licenses/LICENSE
lymph_model-1.3.7.dist-info/METADATA
lymph_model-1.3.7.dist-info/WHEEL
lymph_model-1.3.7.dist-info/top_level.txt
lymph_model-1.3.7.dist-info/RECORD
