Metadata-Version: 2.4
Name: lymph-model
Version: 1.3.7
Summary: Package for statistical modelling of lymphatic metastatic spread.
Author-email: Roman Ludwig <gygqdstu3@mozmail.com>, Yoel Pérez Haas <yoel.perezhaas@usz.ch>, Noemi Bührer <noemi.buehrer@usz.ch>
License: MIT
Project-URL: source, https://github.com/lycosystem/lymph
Project-URL: documentation, https://lymph-model.readthedocs.io
Keywords: cancer,metastasis,lymphatic progression,model
Classifier: Development Status :: 4 - Beta
Classifier: Intended Audience :: Developers
Classifier: Intended Audience :: Science/Research
Classifier: License :: OSI Approved :: MIT License
Classifier: Natural Language :: English
Classifier: Programming Language :: Python
Classifier: Programming Language :: Python :: 3
Classifier: Programming Language :: Python :: 3.10
Classifier: Programming Language :: Python :: 3.11
Classifier: Programming Language :: Python :: 3.12
Classifier: Programming Language :: Python :: 3.13
Classifier: Topic :: Scientific/Engineering
Classifier: Topic :: Software Development :: Libraries
Requires-Python: >=3.10
License-File: LICENSE
Requires-Dist: numpy
Requires-Dist: pandas
Requires-Dist: cachetools
Provides-Extra: tests
Requires-Dist: pytest; extra == "tests"
Requires-Dist: pytest-cov; extra == "tests"
Requires-Dist: scipy; extra == "tests"
Requires-Dist: emcee; extra == "tests"
Provides-Extra: dev
Requires-Dist: pre-commit; extra == "dev"
Requires-Dist: git-cliff; extra == "dev"
Provides-Extra: docs
Requires-Dist: sphinx; extra == "docs"
Requires-Dist: sphinx-book-theme; extra == "docs"
Requires-Dist: sphinx-autodoc-typehints; extra == "docs"
Requires-Dist: myst-nb; extra == "docs"
Requires-Dist: ipython; extra == "docs"
Requires-Dist: matplotlib; extra == "docs"
Requires-Dist: scipy; extra == "docs"
Requires-Dist: emcee; extra == "docs"
Dynamic: license-file
